cli.py
pyctoolbox-0.1.dist-info/METADATA
pyctoolbox-0.1.dist-info/WHEEL
pyctoolbox-0.1.dist-info/entry_points.txt
pyctoolbox-0.1.dist-info/top_level.txt
pyctoolbox-0.1.dist-info/RECORD
