Metadata-Version: 2.1
Name: pyctoolbox
Version: 0.1
Summary: A strong Toolbox for Python Coders
Home-page: https://github.com/pycodersvn/pycoders-toolbox
Author: PyCoders
Author-email: admin@pycoders.vn
License: UNKNOWN
Platform: UNKNOWN
Classifier: Programming Language :: Python :: 3
Classifier: License :: OSI Approved :: MIT License
Classifier: Operating System :: OS Independent
Requires-Python: >=3.6
Requires-Dist: Click
